MANIFEST.in
auth_oauth_data.xml
auth_oauth_data.yml
auth_oauth_view.xml
res_config.xml
res_users.xml
setup.py
./__init__.py
./__openerp__.py
./auth_oauth.py
./res_config.py
./res_users.py
./controllers/__init__.py
./controllers/main.py
i18n/ar.po
i18n/auth_oauth.pot
i18n/cs.po
i18n/de.po
i18n/en_GB.po
i18n/es.po
i18n/fr.po
i18n/hr.po
i18n/hu.po
i18n/it.po
i18n/mk.po
i18n/nb.po
i18n/nl.po
i18n/pl.po
i18n/pt.po
i18n/pt_BR.po
i18n/ro.po
i18n/ru.po
i18n/sl.po
i18n/sv.po
i18n/tr.po
i18n/zh_CN.po
openerp_auth_oauth.egg-info/PKG-INFO
openerp_auth_oauth.egg-info/SOURCES.txt
openerp_auth_oauth.egg-info/dependency_links.txt
openerp_auth_oauth.egg-info/requires.txt
openerp_auth_oauth.egg-info/top_level.txt
security/ir.model.access.csv
static/lib/zocial/sample.html
static/lib/zocial/css/zocial-regular-webfont.eot
static/lib/zocial/css/zocial-regular-webfont.svg
static/lib/zocial/css/zocial-regular-webfont.ttf
static/lib/zocial/css/zocial-regular-webfont.woff
static/src/js/auth_oauth.js
static/src/xml/auth_oauth.xml